{"type":"object","properties":{"id":{"type":"string"},"createdAt":{"type":"string","format":"date-time"},"updatedAt":{"type":"string","format":"date-time"},"firstName":{"type":"string"},"lastName":{"type":"string"},"age":{"type":"number"},"email":{"type":"string"},"phone":{"type":"string"},"bestieFirstName":{"type":"string"},"bestieLastName":{"type":"string"},"bestiePhone":{"type":"string"}},"required":["id","createdAt","updatedAt","firstName","lastName","age","email","phone"],"x-readme-ref-name":"FindOneClientModelSchema"}